primal_page/__init__.py
primal_page/aliases.py
primal_page/bedfiles.py
primal_page/build_index.py
primal_page/config.py
primal_page/dev.py
primal_page/download.py
primal_page/errors.py
primal_page/logging.py
primal_page/main.py
primal_page/modify.py
primal_page/ref_select.py
primal_page/schemas.py
primal_page/validate.py
primal_page-1.12.0.dist-info/METADATA
primal_page-1.12.0.dist-info/WHEEL
primal_page-1.12.0.dist-info/entry_points.txt
primal_page-1.12.0.dist-info/RECORD
