Metadata-Version: 2.4
Name: primal-page
Version: 1.12.0
Summary: Tooling and schemas for the primerschemes index
Project-URL: Repository, https://github.com/ChrisgKent/primal-page
Author-email: ChrisKent <chrisgkent@gmail.com>
Requires-Python: <3.14,>=3.10
Requires-Dist: biopython~=1.83
Requires-Dist: primalbedtools>=1.0.0
Requires-Dist: pydantic<3,>=2.4.2
Requires-Dist: requests<3,>=2.31.0
Requires-Dist: typer>=0.20.0
